omu_chat_youtube/__init__.py
omu_chat_youtube/chat.py
omu_chat_youtube/const.py
omu_chat_youtube/version.py
omu_chat_youtube/youtube.py
omu_chat_youtube/youtubeapi.py
omu_chat_youtube/types/__init__.py
omu_chat_youtube/types/accessibility.py
omu_chat_youtube/types/chatactions.py
omu_chat_youtube/types/contents.py
omu_chat_youtube/types/continuations.py
omu_chat_youtube/types/frameworkupdates.py
omu_chat_youtube/types/image.py
omu_chat_youtube/types/live_chat.py
omu_chat_youtube/types/metadataactions.py
omu_chat_youtube/types/responsecontext.py
omu_chat_youtube/types/runs.py
omu_chat_youtube/types/simpletext.py
omu_chat_youtube/types/tracking.py
omu_chat_youtube/types/updated_metadata.py
omu_chat_youtube/types/urlendpoint.py
omu_chat_youtube/types/youtuberesponse.py
omu_chat_youtube/types/ytcfg.py
omu_chat_youtube/types/ytinitialdata.py
omu_chat_youtube/types/ytinitialplayerresponse.py
omu_chat_youtube-0.9.50.dist-info/METADATA
omu_chat_youtube-0.9.50.dist-info/WHEEL
omu_chat_youtube-0.9.50.dist-info/entry_points.txt
omu_chat_youtube-0.9.50.dist-info/RECORD
