Metadata-Version: 2.4
Name: omu_chat_youtube
Version: 0.9.50
Summary: OMUAPPS Youtube Chat Service
Author-email: am230 <111672334+am230@users.noreply.github.com>
Requires-Python: >=3.12
Requires-Dist: loguru>=0.7.2
Requires-Dist: omu-chatprovider>=0.9.50
